example_package/__init__.py
hello_baamsoo-0.3.1.dist-info/METADATA
hello_baamsoo-0.3.1.dist-info/WHEEL
hello_baamsoo-0.3.1.dist-info/entry_points.txt
hello_baamsoo/.pytest_cache/.gitignore
hello_baamsoo/.pytest_cache/CACHEDIR.TAG
hello_baamsoo/.pytest_cache/README.md
hello_baamsoo/.pytest_cache/v/cache/nodeids
hello_baamsoo/.pytest_cache/v/cache/stepwise
hello_baamsoo/__init__.py
hello_baamsoo/my.py
hello_baamsoo/who.py
hello_baamsoo-0.3.1.dist-info/RECORD
