Metadata-Version: 2.1
Name: hello-baamsoo
Version: 0.3.1
Summary: python program
Author-Email: baamboo <beom5236@gmail.com>
License: MIT
Project-URL: Homepage, https://github.com/baamsoo/hello-baamsoo
Project-URL: Bug tracker, https://github.com/baamsoo/hello-baamsoo/issues
Requires-Python: >=3.8
